pydecoratorxaf/__init__.py
pydecoratorxaf/decoratorxaf.py
pydecoratorxaf-0.0.2.dist-info/METADATA
pydecoratorxaf-0.0.2.dist-info/WHEEL
pydecoratorxaf-0.0.2.dist-info/top_level.txt
pydecoratorxaf-0.0.2.dist-info/RECORD
