Metadata-Version: 2.1
Name: pydecoratorxaf
Version: 0.0.2
Summary: 模块简介
Author: Creedassin
Author-email: 82608372@qq.com
Classifier: Programming Language :: Python :: 3
Classifier: License :: OSI Approved :: MIT License
Classifier: Operating System :: OS Independent
Requires-Python: >=3
